simple_senti_py/__init__.py
simple_senti_py/fileGen.py
simple_senti_py/simpleSentiPy.py
simple_senti_py/util.py
simple_senti_py/wrapper.py
simple_senti_py-0.1.1.dist-info/DESCRIPTION.rst
simple_senti_py-0.1.1.dist-info/METADATA
simple_senti_py-0.1.1.dist-info/RECORD
simple_senti_py-0.1.1.dist-info/WHEEL
simple_senti_py-0.1.1.dist-info/metadata.json
simple_senti_py-0.1.1.dist-info/top_level.txt
